{
  "description": "Fairfield Nostr Pubkey Whitelist",
  "version": "1.0.0",
  "updated": "2024-12-11T00:00:00Z",
  "admins": [
    {
      "pubkey": "ADMIN_PUBKEY_HEX_HERE",
      "name": "Fairfield Admin",
      "roles": ["super-admin"],
      "added": "2024-12-11T00:00:00Z"
    }
  ],
  "users": [
    {
      "pubkey": "USER_PUBKEY_HEX_HERE",
      "name": "Example User",
      "cohorts": ["moomaa-tribe"],
      "status": "approved",
      "added": "2024-12-11T00:00:00Z",
      "approved_by": "ADMIN_PUBKEY_HEX_HERE"
    }
  ],
  "pending": [],
  "banned": []
}
